ysp_postdown/__init__.py
ysp_postdown/cmdline.py
ysp_postdown/ctor.py
ysp_postdown/parser.py
ysp_postdown-1.0.2.dist-info/LICENSE
ysp_postdown-1.0.2.dist-info/METADATA
ysp_postdown-1.0.2.dist-info/WHEEL
ysp_postdown-1.0.2.dist-info/entry_points.txt
ysp_postdown-1.0.2.dist-info/top_level.txt
ysp_postdown-1.0.2.dist-info/RECORD
