Metadata-Version: 2.1
Name: ysp-postdown
Version: 1.0.2
Summary: Generate markdown API document from Postman.
Home-page: https://github.com/ShuiPingYang/YspPostdown
Author: YangShuiPing
Author-email: 18611370423@qq.com
License: UNKNOWN
Platform: UNKNOWN
